junit2htmlreport/__init__.py
junit2htmlreport/__main__.py
junit2htmlreport/common.py
junit2htmlreport/matrix.py
junit2htmlreport/merge.py
junit2htmlreport/parser.py
junit2htmlreport/parserimpl.py
junit2htmlreport/render.py
junit2htmlreport/runner.py
junit2htmlreport/textutils.py
tests/__init__.py
tests/helpers.py
tests/inputfiles.py
tests/test_example_output.py
tests/test_junit2html.py
tests/test_junitparser_render.py
tests/test_matrix.py
tests/test_matrix_stdout.py
tests/test_parser_api.py
tests/test_tojunit.py
junit_report_generator-1.1.0.dist-info/LICENSE
junit_report_generator-1.1.0.dist-info/METADATA
junit_report_generator-1.1.0.dist-info/WHEEL
junit_report_generator-1.1.0.dist-info/entry_points.txt
junit_report_generator-1.1.0.dist-info/top_level.txt
junit_report_generator-1.1.0.dist-info/RECORD
