Metadata-Version: 2.1
Name: junit-report-generator
Version: 1.1.0
Summary: Generate HTML reports from Junit results
Home-page: https://your.new.url
Author: khoa.dong
Author-email: dangkhoa0894@gmail.com
License: License :: OSI Approved :: MIT License
Platform: any
License-File: LICENSE
Requires-Dist: jinja2 >=3.0
